_version.py
clone_auto.py
term_args.py
clone_auto-0.0.5.dist-info/COPYING
clone_auto-0.0.5.dist-info/LICENSE
clone_auto-0.0.5.dist-info/METADATA
clone_auto-0.0.5.dist-info/WHEEL
clone_auto-0.0.5.dist-info/entry_points.txt
clone_auto-0.0.5.dist-info/top_level.txt
clone_auto-0.0.5.dist-info/RECORD
