Metadata-Version: 2.1
Name: clone-auto
Version: 0.0.5
Summary: Clone all public repositories from a user in a GIT server
Author-email: sivefunc <sivefunc@tuta.io>
License: clone-auto <-> Git clone public repositories from a user
Project-URL: Homepage, https://gitlab.com/sivefunc/
Keywords: linux,python3,git,script
Classifier: License :: OSI Approved :: GNU General Public License v3 (GPLv3)
Classifier: Programming Language :: Python
Classifier: Programming Language :: Python :: 3
Requires-Python: >=3.11
License-File: LICENSE
License-File: COPYING
Requires-Dist: requests==2.32.3
